flask_fblogin.py
setup.py
Flask_FBLogin.egg-info/PKG-INFO
Flask_FBLogin.egg-info/SOURCES.txt
Flask_FBLogin.egg-info/dependency_links.txt
Flask_FBLogin.egg-info/not-zip-safe
Flask_FBLogin.egg-info/requires.txt
Flask_FBLogin.egg-info/top_level.txt