Metadata-Version: 1.1
Name: Flask-FBLogin
Version: 0.0.1
Summary: Extends Flask-Login to use Facebook's OAuth2 authorization
Home-page: https://github.com/marksteve/flask-fblogin
Author: Mark Steve Samson
Author-email: hello@marksteve.com
License: MIT
Platform: any
Classifier: Development Status :: 4 - Beta
Classifier: Environment :: Web Environment
Classifier: Intended Audience :: Developers
Classifier: License :: OSI Approved :: MIT License
Classifier: Operating System :: OS Independent
Classifier: Programming Language :: Python
Classifier: Topic :: Internet :: WWW/HTTP :: Dynamic Content
Classifier: Topic :: Software Development :: Libraries :: Python Modules
